postmodel/__init__.py
postmodel/exceptions.py
postmodel/main.py
postmodel/transaction.py
postmodel/ext/__init__.py
postmodel/ext/callflow.py
postmodel/ext/callpy.py
postmodel/ext/sanic.py
postmodel/models/__init__.py
postmodel/models/fields.py
postmodel/models/functions.py
postmodel/models/model.py
postmodel/models/query.py
postmodel/sqldb/__init__.py
postmodel/sqldb/base.py
postmodel/sqldb/common.py
postmodel/sqldb/postgres.py
postmodel-0.3.0.dist-info/LICENSE
postmodel-0.3.0.dist-info/METADATA
postmodel-0.3.0.dist-info/WHEEL
postmodel-0.3.0.dist-info/top_level.txt
postmodel-0.3.0.dist-info/RECORD
