Metadata-Version: 2.1
Name: postmodel
Version: 0.3.0
Summary: Easy async ORM for python, built with relations in mind.
Home-page: https://github.com/zeaphoo/postmodel
Author: Zhuo Wei
Author-email: zeaphoo@qq.com
Maintainer: Zhuo Wei
Maintainer-email: zeaphoo@qq.com
License: MIT License
Project-URL: Source Code, https://github.com/zeaphoo/postmodel/
Project-URL: Issue Tracker, https://github.com/zeaphoo/postmodel/issues/
Classifier: Development Status :: 4 - Beta
Classifier: Intended Audience :: Developers
Classifier: Programming Language :: Python :: 3
Classifier: Programming Language :: Python :: 3.6
Classifier: Programming Language :: Python :: 3.7
Classifier: Programming Language :: Python :: 3.8
Classifier: Programming Language :: Python :: 3.9
Classifier: Programming Language :: Python :: Implementation :: CPython
Classifier: Programming Language :: PL/SQL
Classifier: Framework :: AsyncIO
Classifier: Topic :: Software Development :: Libraries :: Python Modules
Classifier: Topic :: Database
Classifier: Operating System :: POSIX
Requires-Python: >=3.7
License-File: LICENSE
Requires-Dist: pypika >=0.35.21
Requires-Dist: ciso8601 >=2.1.2
Requires-Dist: basepy >=0.3.1
Requires-Dist: asyncpg >=0.20.1
Requires-Dist: contextvars >=2.4 ; python_version < "3.7"
Provides-Extra: dev
Requires-Dist: pytest ; extra == 'dev'
Requires-Dist: pytest-asyncio ; extra == 'dev'
